{
    "titel": "overnight oats met banaan",
    "Ingrediënten": {
        "Havermout": "45 gram",
        "Melk": "100 ml",
        "Kaneel": "1 theelepel",
        "Vanille extract": "1 theelepel", 
        "Yoghurt": "85 gram",
        "Banaan": "1"
    },
    "Steps":{
        "_1": "1. Prak de banaan en voeg de melk toe, meng goed.",
        "_2": "2. Voeg ook de plantaardige yoghurt, kaneel, vanille extract en havermout toe.",  
        "_3": "3. Meng alles goed en zet het mengsel in een afgedekt bakje voor een nachtje in de koelkast.",
        "_4": "4. De volgende ochtend top je het af met jouw favoriete toppings zoals noten, vers fruit, pindakaas of granola.",
        "_5": "5. En je ben klaar!"
    }
}